azure/identity/broker/__init__.py
azure/identity/broker/_browser.py
azure/identity/broker/_utils.py
azure/identity/broker/_version.py
azure/identity/broker/py.typed
azure_identity_broker-1.3.0.dist-info/licenses/LICENSE
azure_identity_broker-1.3.0.dist-info/METADATA
azure_identity_broker-1.3.0.dist-info/WHEEL
azure_identity_broker-1.3.0.dist-info/top_level.txt
azure_identity_broker-1.3.0.dist-info/RECORD
